setup.py
mpttadmin/__init__.py
mpttadmin/mpttadmin.py
mpttadmin.egg-info/PKG-INFO
mpttadmin.egg-info/SOURCES.txt
mpttadmin.egg-info/dependency_links.txt
mpttadmin.egg-info/requires.txt
mpttadmin.egg-info/top_level.txt