Metadata-Version: 1.0
Name: mpttadmin
Version: 0.3
Summary: jstree admin for mptt models
Home-page: http://code.tabed.org/mptt_admin
Author: Mikhail Sakhno
Author-email: pawn13@gmail.com
License: BSD
Keywords: django admin
Platform: POSIX
Classifier: Framework :: Django
Classifier: Intended Audience :: Developers
Classifier: Intended Audience :: System Administrators
Classifier: Operating System :: OS Independent
Classifier: Topic :: Software Development
